aliot/__init__.py
aliot/aliot_obj.py
aliot/constants.py
aliot/decoder.py
aliot/encoder.py
aliot/state.py
aliot/core/__init__.py
aliot/core/_cli/__init__.py
aliot/core/_cli/aliot_cli.py
aliot/core/_cli/cli_service.py
aliot/core/_cli/utils.py
aliot/core/_config/__init__.py
aliot/core/_config/config.py
aliot/core/_config/constants.py
aliot/core/_config/templates.py
aliot/exceptions/__init__.py
aliot/exceptions/should_not_call_error.py
aliot_py-1.0.6.dist-info/METADATA
aliot_py-1.0.6.dist-info/WHEEL
aliot_py-1.0.6.dist-info/entry_points.txt
aliot_py-1.0.6.dist-info/top_level.txt
aliot_py-1.0.6.dist-info/RECORD
