Metadata-Version: 2.1
Name: aliot-py
Version: 1.0.6
Summary: Aliot-py is the python implementation of the Aliot library, an IOT library made to work with the ALIVEIoT ecosystem (see https://alivecode.ca/iot)
Home-page: https://github.com/ALIVEcode/aliot/tree/aliot2
Author: Innovations ALIVEcode inc.
Author-email: alivecode.developers@gmail.com
License: UNKNOWN
Platform: UNKNOWN
Classifier: Programming Language :: Python :: 3
Classifier: Programming Language :: Python :: 3.7
Requires-Python: >=3.7
Requires-Dist: websocket-client ~=1.3.2
Requires-Dist: rich ~=12.3.0
Requires-Dist: click ~=8.1.3
Requires-Dist: requests ~=2.27.1
Requires-Dist: setuptools ==62.1.0
